{
  "date": {
    "Year": 2016,
    "Month": "January",
    "Day": "2"
  },
  "lineLabels": [
    "Jan 20",
    "Jan 21",
    "Jan 22",
    "Jan 23",
    "Jan 24",
    "Jan 25",
    "Jan 26"
  ],
  "lineDefault": "Up to Today",
  "lineProductive": [
    1.6,
    3.5,
    3.5,
    3.433,
    8.184,
    8.1,
    0.383
  ],
  "lineUnproductive": [
    0,
    0,
    4,
    1.483,
    1.834,
    1.333,
    0
  ],
  "barDefault": "week",
  "barHours": [
    28.694,
    8.647,
    3.247,
    0,
    4.597,
    3.131,
    0
  ],
  "barTypes": [
    "Work",
    "Leisure",
    "Daily Routines",
    "Sleeping",
    "Eating",
    "Transportation",
    "Exercise"
  ]
}